django_modeltranslation_xliff-1.0.0b3.dist-info/METADATA
django_modeltranslation_xliff-1.0.0b3.dist-info/RECORD
django_modeltranslation_xliff-1.0.0b3.dist-info/WHEEL
django_modeltranslation_xliff-1.0.0b3.dist-info/top_level.txt
modeltranslation_xliff/__init__.py
modeltranslation_xliff/admin.py
modeltranslation_xliff/apps.py
modeltranslation_xliff/settings.py
modeltranslation_xliff/utils.py
