Metadata-Version: 2.1
Name: django-modeltranslation-xliff
Version: 1.0.0b3
Summary: XLIFF exchange for django-modeltranslation
Home-page: https://github.com/romanvm/django-modeltranslation-xliff
Author: Roman Miroshnychenko
Author-email: roman1972@gmail.com
License: MIT
Platform: UNKNOWN
Classifier: Development Status :: 4 - Beta
Classifier: Environment :: Web Environment
Classifier: Framework :: Django
Classifier: Intended Audience :: Developers
Classifier: License :: OSI Approved :: MIT License
Classifier: Operating System :: OS Independent
Classifier: Programming Language :: Python :: 3 :: Only
Classifier: Topic :: Text Processing :: Linguistic
Requires-Python: >=3.4
Requires-Dist: Django (>=1.11)
Requires-Dist: django-modeltranslation (>=0.13b1)
Requires-Dist: nltk
Requires-Dist: lxml
